[
  {
    "owner": "@Sofzizou",
    "name": "ELBORDJI972",
    "mail": "djamelacc56@gmail.com",
    "password": "Zero2007@.",
    "TokenMail": "fuqz ywbg zaqz homz",
    "profilePhotoId": "https://img.chritout.com/uploads/DevTM_1763588060282/p_fyxf2gur.jpg",
    "membersName": "Individual",
    "locationName": "Oran",
    "visaTypeName": "Visa renewal / renouvellement de visa",
    "category": "primetime",
    "visaSubName": "Oran 2",
    "GmailPasswordApp": "",
    "mailotp": "djamelacc56@gmail.com",
    "microsoftEmail": "djamelacc56@gmail.com"
  }
]