[
  {
    "owner": "@Seifeddinben",
    "name": "MOULOUD900",
    "mail": "seif.ben1@outlook.fr",
    "password": "T411xbox@",
    "TokenMail": "qwup qldo zyjv ivkd",
    "profilePhotoId": "N/A",
    "membersName": "Individual",
    "mailotp": "khadrasaragachi@gmail.com",
    "locationName": "Algiers",
    "visaTypeName": "Visa renewal / renouvellement de visa",
    "category": "primetime",
    "visaSubName": "ALG 2",
    "microsoftEmail": "seif.ben1@outlook.fr",
    "GmailPasswordApp": ""
  }
]