[
  {
    "owner": "@SeifEddinben",
    "name": "yakoub10",
    "mail": "yakoub706@any.pink",
    "password": "T411xbox360@",
    "GmailPasswordApp": "ewmg hfru iqrv krci",
    "profilePhotoId": "https://img.chritout.com/uploads/DevTM_1763734002979/hghgh.jpg",
    "membersName": "Individual",
    "locationName": "Oran",
    "visaTypeName": "National Visa",
    "category": "Prime Time",
    "visaSubName": "Family reunification visa",
    "cardNumber": "6280 7030 5491 8278",
    "cardCvv": "866",
    "cardMonth": "04",
    "cardYear": "2026",
    "cardHolder": "BELHACHAMI FATIMA ZAHR",
    "mailotp": "",
    "microsoftEmail": "yakoub706@any.pink"
  }
]